{
	"$id": "https://snavesutit.github.io/origins-mod-schemas/",
	"title": "Fluid Condition",
	"description": "Fluid Condition Types operate on a FluidState, essentially which fluid (if any) exists, as well as properties of the fluid. These are available to power/condition types that provides a fluid_condition object field.\nType: 'origins:constant'\n- Provides a constant state where it's either true or false. Mainly added as a backup case in case a condition is required in some power/action/condition types.",
	"type": "object",
	"required": [
		"value"
	],
	"properties": {
		"value": {
			"description": "If true, the condition is always fulfilled. If false, the condition is never fulfilled.",
			"type": "boolean"
		}
	}
}