{
	"type": "object",
	"required": [
		"tag"
	],
	"properties": {
		"tag": {
			"$ref": "../types/identifier.json",
			"description": "The namespace and ID of the tag which the block should be in to pass the check.",
			"markdownDescription": "The namespace and ID of the tag which the block should be in to pass the check."
		},
		"type": {
			"description": "\n\n[Block Condition Type](../block_condition_types.md)\n\nChecks whether the block is in a specified tag.\n\nType ID: `origins:in_tag`\n\n\n",
			"markdownDescription": "\n\n[Block Condition Type](../block_condition_types.md)\n\nChecks whether the block is in a specified tag.\n\nType ID: `origins:in_tag`\n\n\n"
		}
	}
}