{
	"type": "object",
	"required": [
		"key"
	],
	"properties": {
		"type": {
			"description": "### ⚠️ Requires [Apugli](https://apugli.readthedocs.io/en/latest/) to be installed! ⚠️\n\n## Custom Projectile\n\n---\n\n\n\n[Entity Action Type](https://apugli.readthedocs.io/en/latest/types/entity_action_types/custom_projectile)\n\nFires a projectile that is customisable by the fields of the entity action type.\n\nType ID: `apugli:custom_projectile`\n\n\n\n\n---\n\n### Examples\n\n```json\n{\n    \"type\": \"apugli:custom_projectile\",\n    \"entity_id\": \"example:realistic_brick\",\n    \"texture_url\": \"https://freepngimg.com/thumb/bricks/8-2-bricks-png.png\",\n    \"bientity_action_on_miss\": {\n      \"type\": \"apoli:target_action\",\n      \"action\": {\n        \"type\": \"apoli:and\",\n        \"actions\": [\n          {\n            \"type\": \"apoli:execute_command\",\n            \"command\": \"playsound minecraft:block.stone.break player @a ~ ~ ~ 1 0.7\"\n          },\n          {\n            \"type\": \"apoli:spawn_particles\",\n            \"particle\": {\n              \"type\": \"minecraft:item\",\n              \"params\": \"minecraft:brick\"\n            },\n            \"count\": 8,\n            \"speed\": 0.1,\n            \"spread\": {\n              \"x\": 2.0,\n              \"y\": 0.0,\n              \"z\": 2.0\n            }\n          }\n        ]\n      }\n    },\n    \"owner_target_bientity_action_on_hit\": {\n      \"type\": \"apoli:and\",\n      \"actions\": [\n        {\n          \"type\": \"apoli:damage\",\n          \"source\": {\n            \"name\": \"brick.player\"\n          },\n          \"amount\": 8\n        }\n      ]\n    },\n    \"count\": 8,\n    \"divergence\": 2.0,\n    \"speed\": 0.8\n}\n```\nThis example action will let an entity fire a custom projectile with the use key, the projectile has the id `example:realistic_brick` and is textured like a high resolution brick. this spawns particles and plays a sound upon missing, and damages entities upon being hit by the brick. The brick flies at a speed of 2.0.",
			"markdownDescription": "### ⚠️ Requires [Apugli](https://apugli.readthedocs.io/en/latest/) to be installed! ⚠️\n\n## Custom Projectile\n\n---\n\n\n\n[Entity Action Type](https://apugli.readthedocs.io/en/latest/types/entity_action_types/custom_projectile)\n\nFires a projectile that is customisable by the fields of the entity action type.\n\nType ID: `apugli:custom_projectile`\n\n\n\n\n---\n\n### Examples\n\n```json\n{\n    \"type\": \"apugli:custom_projectile\",\n    \"entity_id\": \"example:realistic_brick\",\n    \"texture_url\": \"https://freepngimg.com/thumb/bricks/8-2-bricks-png.png\",\n    \"bientity_action_on_miss\": {\n      \"type\": \"apoli:target_action\",\n      \"action\": {\n        \"type\": \"apoli:and\",\n        \"actions\": [\n          {\n            \"type\": \"apoli:execute_command\",\n            \"command\": \"playsound minecraft:block.stone.break player @a ~ ~ ~ 1 0.7\"\n          },\n          {\n            \"type\": \"apoli:spawn_particles\",\n            \"particle\": {\n              \"type\": \"minecraft:item\",\n              \"params\": \"minecraft:brick\"\n            },\n            \"count\": 8,\n            \"speed\": 0.1,\n            \"spread\": {\n              \"x\": 2.0,\n              \"y\": 0.0,\n              \"z\": 2.0\n            }\n          }\n        ]\n      }\n    },\n    \"owner_target_bientity_action_on_hit\": {\n      \"type\": \"apoli:and\",\n      \"actions\": [\n        {\n          \"type\": \"apoli:damage\",\n          \"source\": {\n            \"name\": \"brick.player\"\n          },\n          \"amount\": 8\n        }\n      ]\n    },\n    \"count\": 8,\n    \"divergence\": 2.0,\n    \"speed\": 0.8\n}\n```\nThis example action will let an entity fire a custom projectile with the use key, the projectile has the id `example:realistic_brick` and is textured like a high resolution brick. this spawns particles and plays a sound upon missing, and damages entities upon being hit by the brick. The brick flies at a speed of 2.0."
		},
		"entity_id": {
			"$ref": "../../apoli/types/autocomplete_helpers/entity_identifier.json",
			"description": "An identifier for use with projectiles spawned through this entity action. For use with [Custom Entity Id (Entity Condition Type)](https://apugli.readthedocs.io/en/latest/types/entity_action_types/custom_projectile).",
			"markdownDescription": "An identifier for use with projectiles spawned through this entity action. For use with [Custom Entity Id (Entity Condition Type)](https://apugli.readthedocs.io/en/latest/types/entity_action_types/custom_projectile)."
		},
		"texture_location": {
			"$ref": "../../apoli/types/autocomplete_helpers/texture_location.json",
			"description": "If specified, the texture used for the custom projectile.",
			"markdownDescription": "If specified, the texture used for the custom projectile."
		},
		"texture_url": {
			"type": "string",
			"enum": [
				"texture_location"
			],
			"description": "If specified, the url to a .png file imported into the game as a texture for this power's use. This will be used as a fallback if `texture_location` is not specified or if a texture is not present.",
			"markdownDescription": "If specified, the url to a .png file imported into the game as a texture for this power's use. This will be used as a fallback if `texture_location` is not specified or if a texture is not present."
		},
		"count": {
			"type": "integer",
			"default": 1,
			"description": "The amount of projectiles to fire each use.",
			"markdownDescription": "The amount of projectiles to fire each use."
		},
		"speed": {
			"type": "number",
			"default": 1.5,
			"description": "The speed applied to the fired projectile.",
			"markdownDescription": "The speed applied to the fired projectile."
		},
		"divergence": {
			"type": "number",
			"default": 1,
			"description": "How much each projectile fired is affected by random spread.",
			"markdownDescription": "How much each projectile fired is affected by random spread."
		},
		"sound": {
			"$ref": "../../apoli/types/autocomplete_helpers/sound_identifier.json",
			"description": "If set, the sound with this ID will be played when the power is used.",
			"markdownDescription": "If set, the sound with this ID will be played when the power is used."
		},
		"tag": {
			"$ref": "../../apoli/types/nbt.json",
			"description": "NBT data of the entity.",
			"markdownDescription": "NBT data of the entity."
		},
		"entity_action_before_firing": {
			"$ref": "../../apoli/entity_action.json",
			"description": "If specified, the entity action to execute on the entity firing the projectile just prior to the projectile being created.",
			"markdownDescription": "If specified, the entity action to execute on the entity firing the projectile just prior to the projectile being created."
		},
		"bientity_action_after_firing": {
			"$ref": "../../apoli/bientity_action.json",
			"description": "If specified, the bi-entity action to execute with the projectile owner the actor, and the projectile as the target as soon as the projectile is created.",
			"markdownDescription": "If specified, the bi-entity action to execute with the projectile owner the actor, and the projectile as the target as soon as the projectile is created."
		},
		"block_action_on_hit": {
			"$ref": "../../apoli/block_action.json",
			"description": "If specified, the block action to execute on the block the projectile lands on upon having it land on it.",
			"markdownDescription": "If specified, the block action to execute on the block the projectile lands on upon having it land on it."
		},
		"bientity_action_on_miss": {
			"$ref": "../../apoli/bientity_action.json",
			"description": "If specified, the bi-entity action to execute with the projectile owner as the actor, and the projectile as the target upon missing.",
			"markdownDescription": "If specified, the bi-entity action to execute with the projectile owner as the actor, and the projectile as the target upon missing."
		},
		"bientity_action_on_hit": {
			"$ref": "../../apoli/bientity_action.json",
			"description": "If specified, the bi-entity action to execute with the projectile as the actor, and the hit entity as the target upon hitting an entity.",
			"markdownDescription": "If specified, the bi-entity action to execute with the projectile as the actor, and the hit entity as the target upon hitting an entity."
		},
		"owner_target_bientity_action_on_hit": {
			"$ref": "../../apoli/bientity_action.json",
			"description": "If specified, the bi-entity action to execute with the projectile owner as the actor, and the hit entity as the target upon hitting an entity.",
			"markdownDescription": "If specified, the bi-entity action to execute with the projectile owner as the actor, and the hit entity as the target upon hitting an entity."
		},
		"block_action_cancels_miss_action": {
			"default": "false",
			"$ref": "../../apoli/block_action.json",
			"description": "Determines if the `block_action_on_hit` action will cancel the `bientity_action_on_miss` action.",
			"markdownDescription": "Determines if the `block_action_on_hit` action will cancel the `bientity_action_on_miss` action."
		},
		"block_condition": {
			"$ref": "../../apoli/block_condition.json",
			"description": "If specified, the block condition that the block targeted by the `block_action_on_hit` field must meet in order for that to run.",
			"markdownDescription": "If specified, the block condition that the block targeted by the `block_action_on_hit` field must meet in order for that to run."
		},
		"bientity_condition": {
			"$ref": "../../apoli/bientity_condition.json",
			"description": "If specified, the bi-entity condition with the projectile as the actor and the target as the target for the projectile to actually hit the target instead of pass through.",
			"markdownDescription": "If specified, the bi-entity condition with the projectile as the actor and the target as the target for the projectile to actually hit the target instead of pass through."
		},
		"owner_bientity_condition": {
			"$ref": "../../apoli/bientity_condition.json",
			"description": "If specified, the bi-entity condition with the projectile owner as the actor and the target as the target for the projectile to actually hit the target instead of pass through.",
			"markdownDescription": "If specified, the bi-entity condition with the projectile owner as the actor and the target as the target for the projectile to actually hit the target instead of pass through."
		},
		"tick_bientity_action": {
			"$ref": "../../apoli/bientity_action.json",
			"description": "If specified, the bi-entity action with the projectile owner as the actor, and the projectile as the target that is run each tick of the projectile's lifespan.",
			"markdownDescription": "If specified, the bi-entity action with the projectile owner as the actor, and the projectile as the target that is run each tick of the projectile's lifespan."
		},
		"key": {
			"$ref": "../../apoli/types/key.json",
			"description": "Which active key this power should respond to.",
			"markdownDescription": "Which active key this power should respond to."
		}
	}
}