{
	"type": "object",
	"properties": {
		"item": {
			"$ref": "autocomplete_helpers/item_identifier.json",
			"description": "ID of a registered item.",
			"markdownDescription": "ID of a registered item."
		},
		"amount": {
			"type": "integer",
			"description": "Size of the stack.",
			"markdownDescription": "Size of the stack."
		},
		"tag": {
			"type": "string",
			"description": "NBT data of the item.",
			"markdownDescription": "NBT data of the item."
		},
		"slot": {
			"$ref": "slot.json",
			"description": "Inventory slot position of the stack. If not specified, will be the first free slot in the inventory. See [Positioned Item Stack Slots](https://origins.readthedocs.io/en/latest/types/data_types/positioned_item_stack) for possible values.",
			"markdownDescription": "Inventory slot position of the stack. If not specified, will be the first free slot in the inventory. See [Positioned Item Stack Slots](https://origins.readthedocs.io/en/latest/types/data_types/positioned_item_stack) for possible values."
		}
	}
}